MaxCleanerDB/__init__.py
MaxCleanerDB/main.py
MaxCleanerDB/mdb_ScreenBuffer.py
MaxCleanerDB/mdb_control_file_visibility.py
MaxCleanerDB/mdb_core.py
MaxCleanerDB/mdb_date_change.py
MaxCleanerDB/mdb_loop_progress.py
MaxCleanerDB/mdb_max_clear.py
MaxCleanerDB/mdb_mini_guide.py
MaxCleanerDB/mdb_others.py
MaxCleanerDB/mdb_pretty_print.py
MaxCleanerDB/mdb_session_id_generator.py
MaxCleanerDB/mdb_validations.py
MaxCleanerDB/mdb_wait_queue.py
maxcleanerdb-3.0.9.5.dist-info/METADATA
maxcleanerdb-3.0.9.5.dist-info/WHEEL
maxcleanerdb-3.0.9.5.dist-info/top_level.txt
maxcleanerdb-3.0.9.5.dist-info/RECORD
